setup.py
origin/__init__.py
origin/utils.py
origin.egg-info/PKG-INFO
origin.egg-info/SOURCES.txt
origin.egg-info/dependency_links.txt
origin.egg-info/requires.txt
origin.egg-info/top_level.txt
origin/publisher/__init__.py
origin/publisher/amqp.py
origin/publisher/base.py
origin/publisher/null.py