Metadata-Version: 1.0
Name: origin
Version: 1.0.2
Summary: Python library for the Origin Event Publisher
Home-page: https://www.wizardsofindustry.net
Author: Cochise Ruhulessin
Author-email: cochise.ruhulessin@wizardsofindustry.net
License: UNKNOWN
Platform: UNKNOWN
